conventional_semver/__init__.py
conventional_semver/calculate.py
conventional_semver/conventional_semver.py
conventional_semver/validate.py
conventional_semver-0.2.6.dist-info/LICENSE
conventional_semver-0.2.6.dist-info/METADATA
conventional_semver-0.2.6.dist-info/WHEEL
conventional_semver-0.2.6.dist-info/entry_points.txt
conventional_semver-0.2.6.dist-info/RECORD
