Metadata-Version: 2.1
Name: conventional_semver
Version: 0.2.6
Summary: CLI tool for deciding the next semantic version of the project, using conventional commits.
License: GPLv3
Author: Erik Thorsell
Author-email: erik@thorsell.io
Requires-Python: >=3.12,<4.0
Classifier: License :: Other/Proprietary License
Classifier: Programming Language :: Python :: 3
Classifier: Programming Language :: Python :: 3.12
Requires-Dist: gitpython (>=3.1.40,<4.0.0)
Requires-Dist: loguru (>=0.7.2,<0.8.0)
Requires-Dist: pccc (>=0.4.14,<0.5.0)
Requires-Dist: semantic-version (>=2.10.0,<3.0.0)
